mini_faiss/__init__.py
mini_faiss/_core.cpp
mini_faiss/_core.cpython-314-darwin.so
mini_faiss/_index.hpp
mini_faiss-1.0.0.dist-info/METADATA
mini_faiss-1.0.0.dist-info/WHEEL
mini_faiss-1.0.0.dist-info/licenses/LICENSE
mini_faiss-1.0.0.dist-info/RECORD
