Metadata-Version: 2.2
Name: mini-faiss
Version: 1.0.0
Summary: A minimal, easy-to-understand FAISS-like library for vector similarity search with SIMD acceleration
Keywords: faiss,similarity-search,vector-search,simd,dense-retrieval,embeddings
Author: mini-faiss contributors
License: MIT
Classifier: Development Status :: 4 - Beta
Classifier: Intended Audience :: Developers
Classifier: Intended Audience :: Science/Research
Classifier: License :: OSI Approved :: MIT License
Classifier: Programming Language :: Python :: 3
Classifier: Programming Language :: Python :: 3.8
Classifier: Programming Language :: Python :: 3.9
Classifier: Programming Language :: Python :: 3.10
Classifier: Programming Language :: Python :: 3.11
Classifier: Programming Language :: Python :: 3.12
Classifier: Programming Language :: C++
Classifier: Topic :: Scientific/Engineering
Classifier: Topic :: Scientific/Engineering :: Artificial Intelligence
Classifier: Topic :: Software Development :: Libraries :: Python Modules
Project-URL: Repository, https://github.com/yuuichieguchi/mini_faiss
Project-URL: Documentation, https://github.com/yuuichieguchi/mini_faiss#readme
Project-URL: Issue Tracker, https://github.com/yuuichieguchi/mini_faiss/issues
Requires-Python: >=3.8
Requires-Dist: numpy>=1.20.0
Provides-Extra: dev
Requires-Dist: pytest>=6.0; extra == "dev"
Requires-Dist: numpy>=1.20.0; extra == "dev"
